cloudmesh_azure-4.1.10-py3.9-nspkg.pth
cloudmesh/azure/__init__.py
cloudmesh/azure/__version__.py
cloudmesh/azure/compute/Provider.py
cloudmesh/azure/compute/__init__.py
cloudmesh/azure/compute/test.py
cloudmesh_azure-4.1.10.dist-info/LICENSE
cloudmesh_azure-4.1.10.dist-info/METADATA
cloudmesh_azure-4.1.10.dist-info/WHEEL
cloudmesh_azure-4.1.10.dist-info/namespace_packages.txt
cloudmesh_azure-4.1.10.dist-info/top_level.txt
cloudmesh_azure-4.1.10.dist-info/RECORD
