Metadata-Version: 2.1
Name: cloudmesh-azure
Version: 4.1.10
Summary: A command called azure and foo for the cloudmesh shell
Home-page: https://github.com/cloudmesh/cloudmesh-azure
Author: Gregor von Laszewski
Author-email: laszewski@gmail.com
License: Apache 2.0
Platform: UNKNOWN
Classifier: Development Status :: 5 - Production/Stable
Classifier: Environment :: Web Environment
Classifier: Intended Audience :: Developers
Classifier: License :: OSI Approved :: BSD License
Classifier: Operating System :: OS Independent
Classifier: Programming Language :: Python
Classifier: Programming Language :: Python :: 3
Classifier: Programming Language :: Python :: 3.7
Classifier: Programming Language :: Python :: 3.8
Requires-Dist: cloudmesh-configuration
Requires-Dist: cloudmesh-cmd5
Requires-Dist: cloudmesh-sys
Requires-Dist: cloudmesh-inventory
Requires-Dist: cloudmesh-cloud
Requires-Dist: azure.common
Requires-Dist: azure.cli
Requires-Dist: azure.mgmt.compute
Requires-Dist: azure.mgmt.network
